{
    "black_list": [
      {
        "s": "AMEX:BZC",
        "f": [
          "no data",
          "test symbol"
        ]
      },
      {
        "s": "AMEX:HKOR",
        "f": [
          "no data"
        ]
      },
      {
        "s": "AMEX:TPI",
        "f": [
          "no data"
        ]
      },
      {
        "s": "NASDAQ:ABCW",
        "f": [
          "no data"
        ]
      },
      {
        "s": "NASDAQ:NEWP",
        "f": [
          "no data"
        ]
      },
      {
        "s": "NASDAQ:PULB",
        "f": [
          "no data"
        ]
      },
      {
        "s": "NYSE:ADT",
        "f": [
          "no data"
        ]
      },
      {
        "s": "NYSE:NJ",
        "f": [
          "no data"
        ]
      }
    ]
  }