[
    {
        "name": "pricescale",
        "type": "number"
    },
    {
        "name": "minmov",
        "type": "number"
    },
    {
        "name": "minmove2",
        "type": "number"
    },
    {
        "name": "fractional",
        "type": "text"
    },
    {
        "name": "sector",
        "type": "text"
    },
    {
        "name": "country",
        "type": "text"
    },
    {
        "name": "industry",
        "type": "text"
    },
    {
        "name": "market_cap_basic",
        "type": "fundamental_price"
    },
    {
        "name": "price_earnings_ttm",
        "type": "number"
    },
    {
        "name": "price_earnings_current",
        "type": "number"
    },
    {
        "name": "gross_margin_percent_ttm",
        "type": "percent"
    },
    {
        "name": "operating_margin",
        "type": "percent"
    },
    {
        "name": "beta_1_year",
        "type": "number"
    },
    {
        "name": "ebitda",
        "type": "fundamental_price"
    },
    {
        "name": "ebitda_ttm",
        "type": "fundamental_price"
    },
    {
        "name": "earnings_per_share_basic_ttm",
        "type": "fundamental_price"
    },
    {
        "name": "return_on_assets",
        "type": "percent"
    },
    {
        "name": "return_on_equity",
        "type": "percent"
    },
    {
        "name": "return_of_invested_capital_percent_ttm",
        "type": "percent"
    },
    {
        "name": "total_shares_outstanding",
        "type": "number"
    },
    {
        "name": "total_shares_outstanding_calculated",
        "type": "number"
    },
    {
        "name": "current_ratio",
        "type": "number"
    },
    {
        "name": "current_ratio_current",
        "type": "number"
    },
    {
        "name": "quick_ratio",
        "type": "number"
    },
    {
        "name": "quick_ratio_current",
        "type": "number"
    },
    {
        "name": "total_revenue",
        "type": "fundamental_price"
    },
    {
        "name": "total_revenue_fy",
        "type": "fundamental_price"
    },
    {
        "name": "debt_to_equity",
        "type": "number"
    },
    {
        "name": "debt_to_equity_fq",
        "type": "number"
    },
    {
        "name": "price_earnings_to_growth_ttm",
        "type": "number"
    },
    {
        "name": "price_book_fq",
        "type": "number"
    },
    {
        "name": "price_book_current",
        "type": "number"
    },
    {
        "name": "price_free_cash_flow_current",
        "type": "number"
    },
    {
        "name": "goodwill",
        "type": "fundamental_price"
    },
    {
        "name": "goodwill_fq",
        "type": "fundamental_price"
    },
    {
        "name": "debt_to_assets",
        "type": "number"
    },
    {
        "name": "cash_ratio",
        "type": "number"
    },
    {
        "name": "total_capital",
        "type": "number"
    },
    {
        "name": "long_term_capital",
        "type": "number"
    },
    {
        "name": "net_debt",
        "type": "fundamental_price"
    },
    {
        "name": "net_debt_fq",
        "type": "fundamental_price"
    },
    {
        "name": "total_debt",
        "type": "fundamental_price"
    },
    {
        "name": "total_debt_fq",
        "type": "fundamental_price"
    },
    {
        "name": "revenue_per_employee",
        "type": "fundamental_price"
    },
    {
        "name": "return_on_invested_capital",
        "type": "percent"
    },
    {
        "name": "after_tax_margin",
        "type": "percent"
    },
    {
        "name": "net_margin",
        "type": "percent"
    },
    {
        "name": "pre_tax_margin",
        "type": "percent"
    },
    {
        "name": "gross_margin",
        "type": "percent"
    },
    {
        "name": "dividends_paid",
        "type": "fundamental_price"
    },
    {
        "name": "total_cash_dividends_paid_fy",
        "type": "fundamental_price"
    },
    {
        "name": "basic_eps_net_income",
        "type": "fundamental_price"
    },
    {
        "name": "earnings_per_share_basic_fy",
        "type": "fundamental_price"
    },
    {
        "name": "earnings_per_share_basic_fy_h",
        "type": "num_slice"
    },
    {
        "name": "preferred_dividends",
        "type": "number"
    },
    {
        "name": "net_income",
        "type": "fundamental_price"
    },
    {
        "name": "net_income_fy",
        "type": "fundamental_price"
    },
    {
        "name": "gross_profit",
        "type": "fundamental_price"
    },
    {
        "name": "gross_profit_fy",
        "type": "fundamental_price"
    },
    {
        "name": "number_of_shareholders",
        "type": "number"
    },
    {
        "name": "number_of_shareholders_fy",
        "type": "number"
    },
    {
        "name": "total_shares_outstanding_fundamental",
        "type": "number"
    },
    {
        "name": "total_shares_outstanding_current",
        "type": "number"
    },
    {
        "name": "total_assets",
        "type": "fundamental_price"
    },
    {
        "name": "total_assets_fq",
        "type": "fundamental_price"
    },
    {
        "name": "total_current_assets",
        "type": "fundamental_price"
    },
    {
        "name": "total_current_assets_fq",
        "type": "fundamental_price"
    },
    {
        "name": "debt_to_equity_fq",
        "type": "number"
    },
    {
        "name": "expected_annual_dividends",
        "type": "number"
    },
    {
        "name": "dividends_per_share_fq",
        "type": "fundamental_price"
    },
    {
        "name": "dps_common_stock_prim_issue_fq",
        "type": "fundamental_price"
    },
    {
        "name": "earnings_per_share_diluted_ttm",
        "type": "fundamental_price"
    },
    {
        "name": "enterprise_value_ebitda_ttm",
        "type": "number"
    },
    {
        "name": "enterprise_value_ebitda_current",
        "type": "number"
    },
    {
        "name": "enterprise_value_fq",
        "type": "fundamental_price"
    },
    {
        "name": "price_revenue_ttm",
        "type": "number"
    },
    {
        "name": "price_sales_current",
        "type": "number"
    },
    {
        "name": "beta_5_year",
        "type": "number"
    },
    {
        "name": "beta_3_year",
        "type": "number"
    },
    {
        "name": "number_of_employees",
        "type": "number"
    },
    {
        "name": "number_of_employees_fy",
        "type": "number"
    },
    {
        "name": "last_annual_eps",
        "type": "fundamental_price"
    },
    {
        "name": "earnings_per_share_diluted_fy",
        "type": "fundamental_price"
    },
    {
        "name": "last_annual_revenue",
        "type": "fundamental_price"
    },
    {
        "name": "current_session",
        "type": "text"
    },
    {
        "name": "rtc",
        "type": "price"
    },
    {
        "name": "earnings_release_date",
        "type": "time"
    },
    {
        "name": "earnings_release_next_date",
        "type": "time"
    },
    {
        "name": "earnings_per_share_fq",
        "type": "fundamental_price"
    },
    {
        "name": "earnings_per_share_diluted_fq",
        "type": "fundamental_price"
    },
    {
        "name": "earnings_per_share_forecast_fq",
        "type": "fundamental_price"
    },
    {
        "name": "revenue_fq",
        "type": "fundamental_price"
    },
    {
        "name": "revenue_forecast_fq",
        "type": "fundamental_price"
    },
    {
        "name": "earnings_per_share_forecast_next_fq",
        "type": "fundamental_price"
    },
    {
        "name": "revenue_forecast_next_fq",
        "type": "fundamental_price"
    },
    {
        "name": "dividends_yield",
        "type": "number"
    },
    {
        "name": "price_book_ratio",
        "type": "number"
    },
    {
        "name": "price_annual_book",
        "type": "number"
    },
    {
        "name": "price_sales_ratio",
        "type": "number"
    },
    {
        "name": "price_annual_sales",
        "type": "number"
    },
    {
        "name": "earnings_release_time",
        "type": "number"
    },
    {
        "name": "earnings_release_next_time",
        "type": "number"
    },
    {
        "name": "premarket_open",
        "type": "price"
    },
    {
        "name": "premarket_high",
        "type": "price"
    },
    {
        "name": "premarket_low",
        "type": "price"
    },
    {
        "name": "premarket_close",
        "type": "price"
    },
    {
        "name": "premarket_volume",
        "type": "number"
    },
    {
        "name": "postmarket_open",
        "type": "price"
    },
    {
        "name": "postmarket_high",
        "type": "price"
    },
    {
        "name": "postmarket_low",
        "type": "price"
    },
    {
        "name": "postmarket_close",
        "type": "price"
    },
    {
        "name": "postmarket_volume",
        "type": "number"
    },
    {
        "name": "premarket_time",
        "type": "time"
    },
    {
        "name": "postmarket_time",
        "type": "time"
    },
    {
        "name": "fundamental_currency_code",
        "type": "text"
    },
    {
        "name": "ex_dividend_date_recent",
        "type": "time"
    },
    {
        "name": "amount_recent",
        "type": "fundamental_price"
    },
    {
        "name": "frequency_recent",
        "type": "text"
    },
    {
        "name": "payment_date_recent",
        "type": "time"
    },
    {
        "name": "yield_recent",
        "type": "number"
    },
    {
        "name": "ex_dividend_date_upcoming",
        "type": "time"
    },
    {
        "name": "amount_upcoming",
        "type": "fundamental_price"
    },
    {
        "name": "frequency_upcoming",
        "type": "text"
    },
    {
        "name": "payment_date_upcoming",
        "type": "time"
    },
    {
        "name": "yield_upcoming",
        "type": "number"
    },
    {
        "name": "average_volume",
        "type": "number"
    },
    {
        "name": "float_shares_outstanding",
        "type": "number"
    },
    {
        "name": "float_shares_outstanding_current",
        "type": "number"
    },
    {
        "name": "gross_profit_fq",
        "type": "fundamental_price"
    },
    {
        "name": "index_priority",
        "type": "number"
    },
    {
        "name": "earnings_release_calendar_date",
        "type": "time"
    },
    {
        "name": "earnings_release_next_calendar_date",
        "type": "time"
    },
    {
        "name": "all_time_high",
        "type": "price"
    },
    {
        "name": "all_time_low",
        "type": "price"
    },
    {
        "name": "all_time_open",
        "type": "price"
    },
    {
        "name": "dividend_ex_date_recent",
        "type": "time"
    },
    {
        "name": "dividend_amount_recent",
        "type": "fundamental_price"
    },
    {
        "name": "dividend_frequency_recent",
        "type": "text"
    },
    {
        "name": "dividend_payment_date_recent",
        "type": "time"
    },
    {
        "name": "dividend_yield_recent",
        "type": "number"
    },
    {
        "name": "dividend_ex_date_upcoming",
        "type": "time"
    },
    {
        "name": "dividend_amount_upcoming",
        "type": "fundamental_price"
    },
    {
        "name": "dividend_frequency_upcoming",
        "type": "text"
    },
    {
        "name": "dividend_payment_date_upcoming",
        "type": "time"
    },
    {
        "name": "dividend_yield_upcoming",
        "type": "number"
    },
    {
        "name": "root",
        "type": "text"
    },
    {
        "name": "dps_common_stock_prim_issue_fy",
        "type": "fundamental_price"
    },
    {
        "name": "total_current_liabilities_fq",
        "type": "fundamental_price"
    },
    {
        "name": "earnings_per_share_fq",
        "type": "fundamental_price"
    },
    {
        "name": "earnings_per_share_fy",
        "type": "fundamental_price"
    },
    {
        "name": "price_cash_flow_current",
        "type": "number"
    },
    {
        "name": "eps_diluted_growth_percent_fq",
        "type": "percent"
    },
    {
        "name": "eps_diluted_growth_percent_fy",
        "type": "percent"
    },
    {
        "name": "price_earnings_forward_fy",
        "type": "number"
    },
    {
        "name": "long_term_debt_to_assets_fy",
        "type": "number"
    },
    {
        "name": "long_term_debt_to_assets_fq",
        "type": "number"
    },
    {
        "name": "long_term_debt_to_equity_fq",
        "type": "number"
    },
    {
        "name": "dividend_payout_ratio_percent_fq",
        "type": "percent"
    },
    {
        "name": "dividend_payout_ratio_percent_fy",
        "type": "percent"
    },
    {
        "name": "total_liabilities_fq",
        "type": "fundamental_price"
    },
    {
        "name": "total_liabilities_fy",
        "type": "fundamental_price"
    },
    {
        "name": "provider-id",
        "type": "text"
    },
    {
        "name": "free_cash_flow",
        "type": "fundamental_price"
    },
    {
        "name": "free_cash_flow_fq",
        "type": "fundamental_price"
    },
    {
        "name": "free_cash_flow_fy",
        "type": "fundamental_price"
    },
    {
        "name": "free_cash_flow_ttm",
        "type": "fundamental_price"
    },
    {
        "name": "cash_n_short_term_invest_fq",
        "type": "fundamental_price"
    },
    {
        "name": "cash_n_short_term_invest_fy",
        "type": "fundamental_price"
    },
    {
        "name": "cash_n_equivalents_fq",
        "type": "fundamental_price"
    },
    {
        "name": "cash_n_equivalents_fy",
        "type": "fundamental_price"
    },
    {
        "name": "country_code_fund",
        "type": "text"
    },
    {
        "name": "update-time",
        "type": "number",
        "extract_from": "daily-bar" 
    },
    {
        "name": "total_revenue_fy_h",
        "type": "num_slice"
    },
    {
        "name": "total_revenue_fq_h",
        "type": "num_slice"
    },
    {
        "name": "total_revenue_ttm",
        "type": "fundamental_price"
    },
    {
        "name": "sell_gen_admin_exp_other_fy",
        "type": "fundamental_price"
    },
    {
        "name": "sell_gen_admin_exp_other_ttm",
        "type": "fundamental_price"
    },
    {
        "name": "research_and_dev_fy",
        "type": "fundamental_price"
    },
    {
        "name": "research_and_dev_ttm",
        "type": "fundamental_price"
    },
    {
        "name": "oper_income_fy",
        "type": "fundamental_price"
    },
    {
        "name": "net_income_bef_disc_oper_fy",
        "type": "fundamental_price"
    },
    {
        "name": "total_revenue_ttm_h",
        "type": "num_slice"
    },
    {
        "name": "gross_profit_fq_h",
        "type": "num_slice"
    },
    {
        "name": "gross_profit_fy_h",
        "type": "num_slice"
    },
    {
        "name": "gross_profit_ttm_h",
        "type": "num_slice"
    },
    {
        "name": "ebitda_fq_h",
        "type": "num_slice"
    },
    {
        "name": "ebitda_fy_h",
        "type": "num_slice"
    },
    {
        "name": "ebitda_ttm_h",
        "type": "num_slice"
    },
    {
        "name": "net_income_fq_h",
        "type": "num_slice"
    },
    {
        "name": "net_income_fy_h",
        "type": "num_slice"
    },
    {
        "name": "net_income_ttm_h",
        "type": "num_slice"
    },
    {
        "name": "free_cash_flow_fq_h",
        "type": "num_slice"
    },
    {
        "name": "free_cash_flow_fy_h",
        "type": "num_slice"
    },
    {
        "name": "free_cash_flow_ttm_h",
        "type": "num_slice"
    },
    {
        "name": "earnings_per_share_diluted_fq_h",
        "type": "num_slice"
    },
    {
        "name": "earnings_per_share_diluted_fy_h",
        "type": "num_slice"
    },
    {
        "name": "earnings_per_share_diluted_ttm_h",
        "type": "num_slice"
    },
    {
        "name": "dps_common_stock_prim_issue_fy_h",
        "type": "num_slice"
    },
    {
        "name": "total_assets_fq_h",
        "type": "num_slice"
    },
    {
        "name": "total_assets_fy_h",
        "type": "num_slice"
    },
    {
        "name": "total_debt_fq_h",
        "type": "num_slice"
    },
    {
        "name": "total_debt_fy_h",
        "type": "num_slice"
    },
    {
        "name": "gross_profit_ttm",
        "type": "fundamental_price"
    },
    {
        "name": "enterprise_value_current",
        "type": "fundamental_price"
    },
    {
        "name": "ebit_ttm",
        "type": "fundamental_price"
    },
    {
        "name": "earnings_per_share_forecast_next_fy",
        "type": "fundamental_price"
    },
    {
        "name": "cash_f_operating_activities_ttm",
        "type": "fundamental_price"
    },
    {
        "name": "working_capital_fq",
        "type": "fundamental_price"
    },
    {
        "name": "diluted_shares_outstanding_fq",
        "type": "fundamental_price"
    },
    {
        "name": "total_current_liabilities_fy",
        "type": "fundamental_price"
    },
    {
        "name": "ebitda_fy",
        "type": "fundamental_price"
    },
    {
        "name": "total_debt_fy",
        "type": "fundamental_price"
    },
    {
        "name": "total_assets_fy",
        "type": "fundamental_price"
    },
    {
        "name": "shrhldrs_equity_fq",
        "type": "fundamental_price"
    },
    {
        "name": "shrhldrs_equity_fy",
        "type": "fundamental_price"
    },
    {
        "name": "return_on_assets_fy",
        "type": "final_percent"
    },
    {
        "name": "return_on_equity_fy",
        "type": "final_percent"
    },
    {
        "name": "return_on_invested_capital_fy",
        "type": "final_percent"
    },
    {
        "name": "dividend_payout_ratio_ttm",
        "type": "final_percent"
    },
    {
        "name": "price_target_high",
        "type": "number"
    },
    {
        "name": "price_target_low",
        "type": "number"
    },
    {
        "name": "price_target_median",
        "type": "number"
    },
    {
        "name": "price_target_average",
        "type": "number"
    },
    {
        "name": "recommendation_buy",
        "type": "number"
    },
    {
        "name": "recommendation_sell",
        "type": "number"
    },
    {
        "name": "recommendation_hold",
        "type": "number"
    },
    {
        "name": "recommendation_under",
        "type": "number"
    },
    {
        "name": "recommendation_over",
        "type": "number"
    },
    {
        "name": "recommendation_total",
        "type": "number"
    },
    {
        "name": "recommendation_mark",
        "type": "number"
    },
    {
        "name": "market_cap_perf_1w",
        "type": "number"
    },
    {
        "name": "market_cap_perf_1m",
        "type": "number"
    },
    {
        "name": "market_cap_perf_3m",
        "type": "number"
    },
    {
        "name": "market_cap_perf_6m",
        "type": "number"
    },
    {
        "name": "market_cap_perf_ytd",
        "type": "number"
    },
    {
        "name": "market_cap_perf_1y",
        "type": "number"
    },
    {
        "name": "market_cap_perf_5y",
        "type": "number"
    },
    {
        "name": "dividends_yield_current",
        "type": "final_percent"
    },
    {
        "name": "dividends_yield_fq",
        "type": "final_percent"
    },
    {
        "name": "dividends_yield_fy",
        "type": "final_percent"
    },
    {
        "name": "price_earnings_growth_ttm",
        "type": "number"
    },
    {
        "name": "all_time_high_day",
        "type": "time"
    },
    {
        "name": "all_time_low_day",
        "type": "time"
    }
]
