[
  {
    "name": "pricescale",
    "type": "number"
  },
  {
    "name": "minmov",
    "type": "number"
  },
  {
    "name": "minmove2",
    "type": "number"
  },
  {
    "name": "fractional",
    "type": "text"
  },
  {
    "name": "sector",
    "type": "text"
  },
  {
    "name": "country",
    "type": "text"
  },
  {
    "name": "industry",
    "type": "text"
  },
  {
    "name": "market_cap_basic",
    "type": "number"
  },
  {
    "name": "price_earnings_ttm",
    "type": "number"
  },
  {
    "name": "gross_margin_percent_ttm",
    "type": "percent"
  },
  {
    "name": "operating_margin",
    "type": "percent"
  },
  {
    "name": "beta_1_year",
    "type": "number"
  },
  {
    "name": "ebitda",
    "type": "number"
  },
  {
    "name": "earnings_per_share_basic_ttm",
    "type": "number"
  },
  {
    "name": "return_on_assets",
    "type": "percent"
  },
  {
    "name": "return_on_equity",
    "type": "percent"
  },
  {
    "name": "return_of_invested_capital_percent_ttm",
    "type": "percent"
  },
  {
    "name": "total_shares_outstanding",
    "type": "number"
  },
  {
    "name": "total_shares_outstanding_calculated",
    "type": "number"
  },
  {
    "name": "current_ratio",
    "type": "number"
  },
  {
    "name": "quick_ratio",
    "type": "number"
  },
  {
    "name": "total_revenue",
    "type": "number"
  },
  {
    "name": "debt_to_equity",
    "type": "number"
  },
  {
    "name": "price_earnings_to_growth_ttm",
    "type": "number"
  },
  {
    "name": "price_book_fq",
    "type": "number"
  },
  {
    "name": "price_free_cash_flow_ttm",
    "type": "number"
  },
  {
    "name": "goodwill",
    "type": "number"
  },
  {
    "name": "debt_to_assets",
    "type": "number"
  },
  {
    "name": "cash_ratio",
    "type": "number"
  },
  {
    "name": "total_capital",
    "type": "number"
  },
  {
    "name": "long_term_capital",
    "type": "number"
  },
  {
    "name": "net_debt",
    "type": "number"
  },
  {
    "name": "total_debt",
    "type": "number"
  },
  {
    "name": "revenue_per_employee",
    "type": "number"
  },
  {
    "name": "return_on_invested_capital",
    "type": "percent"
  },
  {
    "name": "after_tax_margin",
    "type": "percent"
  },
  {
    "name": "pre_tax_margin",
    "type": "percent"
  },
  {
    "name": "gross_margin",
    "type": "percent"
  },
  {
    "name": "dividends_paid",
    "type": "number"
  },
  {
    "name": "basic_eps_net_income",
    "type": "number"
  },
  {
    "name": "preferred_dividends",
    "type": "number"
  },
  {
    "name": "net_income",
    "type": "number"
  },
  {
    "name": "gross_profit",
    "type": "number"
  },
  {
    "name": "number_of_shareholders",
    "type": "number"
  },
  {
    "name": "total_shares_outstanding_fundamental",
    "type": "number"
  },
  {
    "name": "total_assets",
    "type": "number"
  },
  {
    "name": "total_current_assets",
    "type": "number"
  },
  {
    "name": "debt_to_equity_fq",
    "type": "number"
  },
  {
    "name": "expected_annual_dividends",
    "type": "number"
  },
  {
    "name": "dividends_per_share_fq",
    "type": "number"
  },
  {
    "name": "earnings_per_share_diluted_ttm",
    "type": "number"
  },
  {
    "name": "enterprise_value_ebitda_ttm",
    "type": "number"
  },
  {
    "name": "enterprise_value_fq",
    "type": "number"
  },
  {
    "name": "price_revenue_ttm",
    "type": "number"
  },
  {
    "name": "beta_5_year",
    "type": "number"
  },
  {
    "name": "beta_3_year",
    "type": "number"
  },
  {
    "name": "number_of_employees",
    "type": "number"
  },
  {
    "name": "last_annual_eps",
    "type": "number"
  },
  {
    "name": "last_annual_revenue",
    "type": "number"
  },
  {
    "name": "current_session",
    "type": "text"
  },
  {
    "name": "rtc",
    "type": "price"
  },
  {
    "name": "earnings_release_date",
    "type": "time"
  },
  {
    "name": "earnings_release_next_date",
    "type": "time"
  },
  {
    "name": "earnings_per_share_fq",
    "type": "number"
  },
  {
    "name": "earnings_per_share_forecast_fq",
    "type": "number"
  },
  {
    "name": "revenue_fq",
    "type": "number"
  },
  {
    "name": "revenue_forecast_fq",
    "type": "number"
  },
  {
    "name": "earnings_per_share_forecast_next_fq",
    "type": "number"
  },
  {
    "name": "revenue_forecast_next_fq",
    "type": "number"
  },
  {
    "name": "dividends_yield",
    "type": "number"
  },
  {
    "name": "price_book_ratio",
    "type": "number"
  },
  {
    "name": "price_sales_ratio",
    "type": "number"
  },
  {
    "name": "earnings_release_time",
    "type": "number"
  },
  {
    "name": "earnings_release_next_time",
    "type": "number"
  },
  {
    "name": "premarket_open",
    "type": "price"
  },
  {
    "name": "premarket_high",
    "type": "price"
  },
  {
    "name": "premarket_low",
    "type": "price"
  },
  {
    "name": "premarket_close",
    "type": "price"
  },
  {
    "name": "premarket_volume",
    "type": "number"
  },
  {
    "name": "postmarket_open",
    "type": "price"
  },
  {
    "name": "postmarket_high",
    "type": "price"
  },
  {
    "name": "postmarket_low",
    "type": "price"
  },
  {
    "name": "postmarket_close",
    "type": "price"
  },
  {
    "name": "postmarket_volume",
    "type": "number"
  },
  {
    "name": "premarket_time",
    "type": "time"
  },
  {
    "name": "postmarket_time",
    "type": "time"
  },
  {
    "name": "fundamental_currency_code",
    "type": "text"
  },
  {
    "name": "ex_dividend_date_recent",
    "type": "time"
  },
  {
    "name": "amount_recent",
    "type": "number"
  },
  {
    "name": "frequency_recent",
    "type": "text"
  },
  {
    "name": "payment_date_recent",
    "type": "time"
  },
  {
    "name": "yield_recent",
    "type": "number"
  },
  {
    "name": "ex_dividend_date_upcoming",
    "type": "time"
  },
  {
    "name": "amount_upcoming",
    "type": "number"
  },
  {
    "name": "frequency_upcoming",
    "type": "text"
  },
  {
    "name": "payment_date_upcoming",
    "type": "time"
  },
  {
    "name": "yield_upcoming",
    "type": "number"
  },
  {
    "name": "average_volume",
    "type": "number"
  },
  {
    "name": "float_shares_outstanding",
    "type": "number"
  },
  {
    "name": "gross_profit_fq",
    "type": "number"
  },
  {
    "name": "index_priority",
    "type": "number"
  },
  {
    "name": "earnings_release_calendar_date",
    "type": "time"
  },
  {
    "name": "earnings_release_next_calendar_date",
    "type": "time"
  },
  {
    "name": "all_time_high",
    "type": "price"
  },
  {
    "name": "all_time_low",
    "type": "price"
  },
  {
    "name": "dividend_ex_date_recent",
    "type": "time"
  },
  {
    "name": "dividend_amount_recent",
    "type": "number"
  },
  {
    "name": "dividend_frequency_recent",
    "type": "text"
  },
  {
    "name": "dividend_payment_date_recent",
    "type": "time"
  },
  {
    "name": "dividend_yield_recent",
    "type": "number"
  },
  {
    "name": "dividend_ex_date_upcoming",
    "type": "time"
  },
  {
    "name": "dividend_amount_upcoming",
    "type": "number"
  },
  {
    "name": "dividend_frequency_upcoming",
    "type": "text"
  },
  {
    "name": "dividend_payment_date_upcoming",
    "type": "time"
  },
  {
    "name": "dividend_yield_upcoming",
    "type": "number"
  },
  {
    "name": "root",
    "type": "text"
  },
  {
    "name": "dps_common_stock_prim_issue_fy",
    "type": "number"
  },
  {
    "name": "total_liabilities_fq",
    "type": "number"
  },
  {
    "name": "total_liabilities_fy",
    "type": "number"
  },
  {
    "name": "rtc_time",
    "type": "time"
  },
  {
    "name": "lp_time",
    "type": "time"
  }
]
