[{
	"name": "sector",
	"type": "text"
},
{
	"name": "industry",
	"type": "text"
},
{
	"name": "market_cap_basic",
	"type": "number"
},
{
	"name": "price_earnings_ttm",
	"type": "number"
},
{
	"name": "gross_margin_percent_ttm",
	"type": "percent"
},
{
	"name": "operating_margin",
	"type": "percent"
},
{
	"name": "price_52_week_high",
	"type": "price"
},
{
	"name": "price_52_week_low",
	"type": "price"
},
{
	"name": "beta_1_year",
	"type": "number"
},
{
	"name": "average_volume",
	"type": "number"
},
{
	"name": "ebitda",
	"type": "number"
},
{
	"name": "earnings_per_share_basic_ttm",
	"type": "number"
},
{
	"name": "return_on_assets",
	"type": "percent"
},
{
	"name": "return_on_equity",
	"type": "percent"
},
{
	"name": "return_of_invested_capital_percent_ttm",
	"type": "percent"
},
{
	"name": "total_shares_outstanding",
	"type": "number"
},
{
	"name": "current_ratio",
	"type": "number"
},
{
	"name": "quick_ratio",
	"type": "number"
},
{
	"name": "total_revenue",
	"type": "number"
},
{
	"name": "debt_to_equity",
	"type": "number"
},
{
	"name": "price_earnings_to_growth_ttm",
	"type": "number"
},
{
	"name": "price_book_fq",
	"type": "number"
},
{
	"name": "price_free_cash_flow_ttm",
	"type": "number"
}]